gladepaypython/__init__.py
gladepaypython/baseapi.py
gladepaypython/errors.py
gladepaypython/gladepay.py
gladepaypython/utils.py
gladepaypython/version.py
gladepaypython-0.1.4.dist-info/LICENSE.md
gladepaypython-0.1.4.dist-info/METADATA
gladepaypython-0.1.4.dist-info/WHEEL
gladepaypython-0.1.4.dist-info/top_level.txt
gladepaypython-0.1.4.dist-info/RECORD
