Metadata-Version: 2.1
Name: gladepaypython
Version: 0.1.4
Summary: Python wrapper for Gladepay API
Home-page: https://gitlab.com/gladepay-apis/gladepay-python
Author: Chinaka I. Light
Author-email: light@yottabitconsulting.com
License: MIT
Platform: UNKNOWN
Requires-Dist: requests
Requires-Dist: nose2
